Workbook
Name Activo: 0.09
Name Decision: #N/A
Name Endeudamiento: 0.52
Name Intereses: 5.45
Name Liquidez: 1.57
Name PARTICIPACION: #N/A
Name Patrimonio: 0.2
Name Procedencia: #N/A
Name SM_24: 1300000
Name tipo: #N/A
Name Trabajo: 3049134825
Name x: #REF!

Sheet CheckList
A2: Cronograma

Sheet FichaTecnica
B2: FT-094-CO V.4
B3: 44805
A6: FICHA TÉCNICA
A8: Nombre Proyecto
A9: Tipo de Proceso
A10: Entidad
A11: Objeto del Contrato / Alcance
A12: Presupuesto
A13: Presupuesto en SMMLV | B13: =B12/1750905 -> 0
A14: Tiempo de Ejecución
A15: Modalidad de ejecución
A16: Ciudad del proyecto
A17: Valoración
A18: Códigos de RUP (Clasificador de Bienes y Servicios)
A19: Requisitos e Indicadores financieros | B19: Indicadores financieros | C19: SOFTGIC | D19: REQUERIDO
B20: Índice de Liquidez | C20: =IndicadoresSG!C18 -> 2.04 | E20: Mayor o igual | F20: 2.04
B21: Índice de Endeudamiento | C21: =IndicadoresSG!C19 -> 0.3 | E21: Menoro igual | F21: 0.3
B22: Razón de Cobertura a intereses | C22: =IndicadoresSG!C20 -> 2037.98 | E22: Mayor o igual | F22: 2037.98
B23: Capital de Trabajo | C23: =IndicadoresSG!C21 -> 3278055000 | E23: Mayor o igual
B24: Patrimonio | C24: 7137635000
B25: Indicadores organizacionales | C25: SOFTGIC
B26: Rentabilidad del patrimonio | C26: =IndicadoresSG!C23 -> 0.07 | E26: Mayor o igual | F26: 0.07
B27: Rentabilidad del activo | C27: =IndicadoresSG!C24 -> 0.05 | E27: Mayor o igual | F27: 0.05
A28: CRONOGRAMA PLIEGOS

Sheet Documentacion
F2: FT-094-CO V.4
F3: 44805
A5: FICHA TÉCNICA
C8: # Actividades | D8: Act. Realizadas | E8: % de avance
C9: =COUNTIF(E13:E106,"*") -> 0 | D9: =COUNTIF(E13:E106,"Cerrada") -> 0 | E9: =D9/C9*100 -> #DIV/0!
A11: DOCUMENTACIÓN REQUERIDA
A12: ID | B12: Documento | C12: Aplica: Certificado de experiencia, nombre de profesional, puntaje a asignar | E12: ESTADO | F12: Observaciones

Sheet Costeo
C2: Antes de IVA | D2: Con Iva
B3: Valor Presupuesto | C3: =D3/1.19 -> 0 | D3: =FichaTecnica!B12 -> 0
B4: Duración (meses) | C4: 0
B5: Base Horas | C5: 176
B6: Duración Garantía (meses) | C6: 0
B7: % Descuento | C7: 0
C8: Antes de IVA | D8: Con Iva
B9: Valor Propuesta | C9: =C3*(1-C7) -> 0 | D9: =C9*(1+19%) -> 0
B10: % Utilidad | C10: =(C9-C20)/C9 -> #DIV/0!
B11: $ Utilidad | C11: =C9-C20 -> 0
B12: Costos
B13: Personal | C13: =H32 -> 0
B14: Administrativo | C14: =C9*10% -> 0
B15: Licenciamiento | C15: 0
B16: Pólizas | C16: =+Pólizas!J26 -> 0
B17: Garantía | C17: =P32 -> 0
B18: Capacitación | C18: =V31 -> 0
B19: Bonificación | C19: 0
C20: =SUM(C13:C19) -> 0
B22: Personal | J22: Garantía | Q22: Capacitación
B23: Perfil | C23: Cantidad | D23: Salario | E23: % Asignación | F23: +54% prestacional | G23: PC y Licencias | H23: TOTAL | K23: Perfil | L23: Salario | M23: +54% prestacional | N23: PC y Licencias | O23: % Asignación | P23: TOTAL | R23: Perfil | S23: Salario | T23: +54% prestacional | U23: Total Horas | V23: TOTAL
B24: Gerente de proyectos | F24: =D24*(1+54%) -> 0 | G24: 250000 | H24: =SUM(F24:G24)*E24*$C$4*C24 -> 0 | M24: =L24*(1+54%) -> 0 | N24: =180000+(15*3000) -> 225000 | P24: =SUM(M24:N24)*O24*$C$6 -> 0 | T24: =S24*(1+54%) -> 0 | V24: =(T24/240)*U24 -> 0
F25: =D25*(1+54%) -> 0 | G25: 250000 | H25: =SUM(F25:G25)*E25*$C$4*C25 -> 0 | T25: =S25*(1+54%) -> 0 | V25: =(T25/240)*U25 -> 0
F26: =D26*(1+54%) -> 0 | G26: 250000 | H26: =SUM(F26:G26)*E26*$C$4*C26 -> 0
F27: =D27*(1+54%) -> 0 | G27: 250000 | H27: =SUM(F27:G27)*E27*$C$4*C27 -> 0
F28: =D28*(1+54%) -> 0 | G28: 250000 | H28: =SUM(F28:G28)*E28*$C$4*C28 -> 0
F29: =D29*(1+54%) -> 0 | G29: 250000 | H29: =SUM(F29:G29)*E29*$C$4*C29 -> 0
F30: =D30*(1+54%) -> 0 | G30: 250000 | H30: =SUM(F30:G30)*E30*$C$4*C30 -> 0
F31: =D31*(1+54%) -> 0 | G31: 250000 | H31: =SUM(F31:G31)*E31*$C$4*C31 -> 0
H32: =SUM(H24:H31) -> 0 | P32: =SUM(P24:P26) -> 0 | Q32: =SUM(Q24:Q26) -> 0 | V32: =SUM(V24:V26) -> 0
B42: ¿Cómo evalúan la oferta económica? Menor valor
B43: ¿Cómo esta establecido el formato para la presentación de la oferta económica?
B44: ¿Cómo nos van a pagar?
B45: ¿El porcentaje de asignación de los perfiles?
B46: ¿El servicio es presencial o remoto?
B47: ¿Tiene Garantía? ¿Cuánto tiempo?
B48: ¿ANS de atención (7x24, 5x9, 5x25, etc.)? El tiempo de atención mide desde que se crea el ticket hasta que la mesa de servicio toma propiedad, en modalidad 5X8
B49: ¿La oferta incluye ofrecimientos adicionales (bolsa de horas, capacitación, perfiles sin costo)?
B50: ¿Sobre que tecnología esta el requerimiento (App, Sistema de información, etc.)?

Sheet Perfiles
B2: Perfiles
B3: Rol | C3: Requicitos

Sheet Pólizas
B3: Valor del Contrato | C3: Desde | D3: Hasta | E3: Días | F3: Meses | H3: * Diligencias únicamente los espacios en color azul
B4: =FichaTecnica!B12 -> 0 | E4: =+D4-C4 -> 0 | F4: =(DAYS360(C4,D4,FALSE))/360 -> 0
B6: Garantía | C6: Porcentaje | D6: Vr. Asegurado | E6: Desde | F6: Hasta | G6: Días | H6: Tasa | I6: Prorrata | J6: Prima | K6: IVA | L6: PRIMA TOTAL
B7: Seriedad | C7: 0 | D7: =+$B$4*C7 -> 0 | G7: =+F7-E7 -> 0 | H7: 0.0015 | I7: =+(D7*H7)*G7/365 -> 0 | J7: =IF(C7=0,0,IF(D7*H7<30000,30000,D7*H7)) -> 0 | K7: =J7*0.19 -> 0 | L7: =J7+K7 -> 0
B8: Cumplimiento | C8: 0 | D8: =+$B$4*C8 -> 0 | G8: =+F8-E8 -> 0 | H8: 0.003 | I8: =+(D8*H8)*G8/365 -> 0 | J8: =IF(I8=0,0,IF(I8<30000,30000,I8)) -> 0 | K8: =J8*0.19 -> 0 | L8: =J8+K8 -> 0
B9: Buen manejo del anticipo | C9: 0 | D9: =+$B$4*C9 -> 0 | G9: =+F9-E9 -> 0 | H9: 0.003 | I9: =+(D9*H9)*G9/365 -> 0 | J9: =IF(I9=0,0,IF(I9<30000,30000,I9)) -> 0 | K9: =J9*0.19 -> 0 | L9: =J9+K9 -> 0
B10: Pago de Salarios | C10: 0 | D10: =+$B$4*C10 -> 0 | G10: =+F10-E10 -> 0 | H10: 0.0025 | I10: =+(D10*H10)*G10/365 -> 0 | J10: =IF(I10=0,0,IF(I10<30000,30000,I10)) -> 0 | K10: =J10*0.19 -> 0 | L10: =J10+K10 -> 0
B11: Estabilidad | C11: 0 | D11: =+$B$4*C11 -> 0 | G11: =+F11-E11 -> 0 | H11: 0.003 | I11: =+(D11*H11)*G11/365 -> 0 | J11: =IF(I11=0,0,IF(I11<30000,30000,I11)) -> 0 | K11: =J11*0.19 -> 0 | L11: =J11+K11 -> 0
B12: Calidad | C12: 0 | D12: =+$B$4*C12 -> 0 | G12: =+F12-E12 -> 0 | H12: 0.003 | I12: =+(D12*H12)*G12/365 -> 0 | J12: =IF(I12=0,0,IF(I12<30000,30000,I12)) -> 0 | K12: =J12*0.19 -> 0 | L12: =J12+K12 -> 0
I13: TOTALES | J13: =SUM(J7:J12) -> 0 | K13: =SUM(K7:K12) -> 0 | L13: =SUM(L7:L12) -> 0
C14: Total V.A | D14: =SUM(D7:D12) -> 0
J15: Subtotal | L15: =SUM(L7:L12) -> 0
J16: Gastos Expedición
J17: IVA | L17: =(J13+L16)*19% -> 0
J18: Total | L18: =+J13+L16+L17 -> 0
B20: Garantía | C20: Porcentaje | D20: Vr. Asegurado | E20: Desde | F20: Hasta | G20: Días | H20: Tasa | I20: Prorrata | J20: Prima
B21: R.C.E. | C21: 0 | G21: =F21-E21 -> 0 | H21: 0.003 | I21: =+(D21*H21)*G21/365 -> 0 | J21: =IF(I21=0,0,IF(I21<50000,50000,I21)) -> 0
H22: Subtotal | J22: =+J21 -> 0
B23: DEDUCIBLE: | C23: =IF(D21<=10000000,"10% mínimo 1 SMMLV",IF(AND(D21>10000000,D21<=30000000),"10% mínimo 2 SMMLV",IF(AND(D21>30000000,D21<=50000000),"10% mínimo 3 SMMLV","15% mínimo 3 SMMLV"))) -> 10% mínimo 1 SMMLV | H23: IVA | J23: =+J22*19% -> 0
H24: Total | J24: =+J22+J23 -> 0
J26: =L18+J24 -> 0

Sheet Precios art. bajos 
A1: PRECIO ARTIFICIALMENTE BAJO
A3: MÁS DE 5 OFERTAS | D3: CALCULO PRECIO ARTIFICIALMENTE BAJO
A5: PRESUPUESTO OFICIAL | B5: =FichaTecnica!B12 -> 0
A7: PROPONENTE 1 | B7: 0
A8: PROPONENTE 2 | B8: 0
A9: PROPONENTE 3 | B9: 0
A10: PROPONENTE 4 | B10: 0
A11: PROPONENTE 5 | B11: 0
A12: PROPONENTE 6 | B12: 0 | D12: DESVIACION ESTANDAR | E12: =_xlfn.STDEV.S(B7:B16) -> 0
A13: PROPONENTE 7 | B13: 0 | D13: MEDIANA | E13: =MEDIAN(B7:B16) -> 0
A14: PROPONENTE 8 | B14: 0
A15: PROPONENTE 9 | B15: 0 | D15: VALOR MINIMO ACEPTABLE = MEDIANA -DESVIACION ESTANDAR
A16: PROPONENTE 10 | B16: 0 | D16: =E13-E12 -> 0
G19: ELABORADO POR:

Sheet Análisis Ppta Económica
F2: Máximo puntos
B3: Con IVA
A4: PPTO | B4: =FichaTecnica!B12 -> 0 | F4: Media aritmética | G4: Media Armónica | H4: Media Geométrica | I4: Menor Valor | J4: Media Aritmética Alta | K4: Media Geométrica con ppto Oficial
F5: =AVERAGEIF(C6:C14,"x",B6:B14) -> 0 | G5: =HARMEAN(B6,B7,B8,B9,B10,B11,B12,B13,B14) -> #NUM! | H5: =GEOMEAN(B8,B10,B11,B12,B13,B14,B9,B6,B7) -> #NUM! | I5: {=MIN(IF(C6:C14="x",B6:B14))} -> 0 | J5: {=(MAX(IF(C6:C14="x",MAX(B6:B14)+(AVERAGEIF(C6:C14,"x",B6:B14))))/2)} -> 0 | K5: =GEOMEAN(B4,B9,B10,B11,B12,B13,B14,B8,B6,B7) -> #NUM!
A6: Empresa 1 | B6: =+B$4*(1-D6) -> 0 | C6: X | D6: 0.01 | F6: =IF(B6<=$F$5,$G$2*(1-(($F$5-B6)/$F$5)),$G$2*(1-(2*(ABS($F$5-B6)/$F$5)))) -> #DIV/0! | G6: =IF(B6<=$G$5,$G$2*(1-(($G$5-B6)/$G$5)),$G$2*(1-(2*(ABS($G$5-B6)/$G$5)))) -> #NUM! | H6: =IF(B6<=$H$5,$G$2*(1-(($H$5-B6)/$H$5)),$G$2*(1-(2*(ABS($H$5-B6)/$H$5)))) -> #NUM! | I6: =IF(B6<=$I$5,$G$2*(1-(($I$5-B6)/$I$5)),$G$2*(1-(2*(ABS($I$5-B6)/$I$5)))) -> #DIV/0! | J6: =IF(B6<=$J$5,$G$2*(1-(($J$5-B6)/$J$5)),$G$2*(1-2*(ABS($J$5-B6)/$J$5))) -> #DIV/0! | K6: =IF(B6<=$K$5,(1-(($K$5-B6)/$K$5))*$G$2,(1-2*(ABS($K$5-B6))/$K$5)*$G$2) -> #NUM!
A7: Empresa 2 | B7: =+B$4*(1-D7) -> 0 | C7: x | D7: 0.02 | F7: =IF(B7<=$F$5,$G$2*(1-(($F$5-B7)/$F$5)),$G$2*(1-(2*(ABS($F$5-B7)/$F$5)))) -> #DIV/0! | G7: =IF(B7<=$G$5,$G$2*(1-(($G$5-B7)/$G$5)),$G$2*(1-(2*(ABS($G$5-B7)/$G$5)))) -> #NUM! | H7: =IF(B7<=$H$5,$G$2*(1-(($H$5-B7)/$H$5)),$G$2*(1-(2*(ABS($H$5-B7)/$H$5)))) -> #NUM! | I7: =IF(B7<=$I$5,$G$2*(1-(($I$5-B7)/$I$5)),$G$2*(1-(2*(ABS($I$5-B7)/$I$5)))) -> #DIV/0! | J7: =IF(B7<=$J$5,$G$2*(1-(($J$5-B7)/$J$5)),$G$2*(1-2*(ABS($J$5-B7)/$J$5))) -> #DIV/0! | K7: =IF(B7<=$K$5,(1-(($K$5-B7)/$K$5))*$G$2,(1-2*(ABS($K$5-B7))/$K$5)*$G$2) -> #NUM!
A8: Empresa 3 | B8: =+B$4*(1-D8) -> 0 | C8: x | D8: 0.03 | F8: =IF(B8<=$F$5,$G$2*(1-(($F$5-B8)/$F$5)),$G$2*(1-(2*(ABS($F$5-B8)/$F$5)))) -> #DIV/0! | G8: =IF(B8<=$G$5,$G$2*(1-(($G$5-B8)/$G$5)),$G$2*(1-(2*(ABS($G$5-B8)/$G$5)))) -> #NUM! | H8: =IF(B8<=$H$5,$G$2*(1-(($H$5-B8)/$H$5)),$G$2*(1-(2*(ABS($H$5-B8)/$H$5)))) -> #NUM! | I8: =IF(B8<=$I$5,$G$2*(1-(($I$5-B8)/$I$5)),$G$2*(1-(2*(ABS($I$5-B8)/$I$5)))) -> #DIV/0! | J8: =IF(B8<=$J$5,$G$2*(1-(($J$5-B8)/$J$5)),$G$2*(1-2*(ABS($J$5-B8)/$J$5))) -> #DIV/0! | K8: =IF(B8<=$K$5,(1-(($K$5-B8)/$K$5))*$G$2,(1-2*(ABS($K$5-B8))/$K$5)*$G$2) -> #NUM!
A9: Empresa 4 | B9: =+B$4*(1-D9) -> 0 | C9: x | D9: 0.04 | F9: =IF(B9<=$F$5,$G$2*(1-(($F$5-B9)/$F$5)),$G$2*(1-(2*(ABS($F$5-B9)/$F$5)))) -> #DIV/0! | G9: =IF(B9<=$G$5,$G$2*(1-(($G$5-B9)/$G$5)),$G$2*(1-(2*(ABS($G$5-B9)/$G$5)))) -> #NUM! | H9: =IF(B9<=$H$5,$G$2*(1-(($H$5-B9)/$H$5)),$G$2*(1-(2*(ABS($H$5-B9)/$H$5)))) -> #NUM! | I9: =IF(B9<=$I$5,$G$2*(1-(($I$5-B9)/$I$5)),$G$2*(1-(2*(ABS($I$5-B9)/$I$5)))) -> #DIV/0! | J9: =IF(B9<=$J$5,$G$2*(1-(($J$5-B9)/$J$5)),$G$2*(1-2*(ABS($J$5-B9)/$J$5))) -> #DIV/0! | K9: =IF(B9<=$K$5,(1-(($K$5-B9)/$K$5))*$G$2,(1-2*(ABS($K$5-B9))/$K$5)*$G$2) -> #NUM!
A10: Empresa 5 | B10: =+B$4*(1-D10) -> 0 | C10: x | D10: 0.05 | F10: =IF(B10<=$F$5,$G$2*(1-(($F$5-B10)/$F$5)),$G$2*(1-(2*(ABS($F$5-B10)/$F$5)))) -> #DIV/0! | G10: =IF(B10<=$G$5,$G$2*(1-(($G$5-B10)/$G$5)),$G$2*(1-(2*(ABS($G$5-B10)/$G$5)))) -> #NUM! | H10: =IF(B10<=$H$5,$G$2*(1-(($H$5-B10)/$H$5)),$G$2*(1-(2*(ABS($H$5-B10)/$H$5)))) -> #NUM! | I10: =IF(B10<=$I$5,$G$2*(1-(($I$5-B10)/$I$5)),$G$2*(1-(2*(ABS($I$5-B10)/$I$5)))) -> #DIV/0! | J10: =IF(B10<=$J$5,$G$2*(1-(($J$5-B10)/$J$5)),$G$2*(1-2*(ABS($J$5-B10)/$J$5))) -> #DIV/0! | K10: =IF(B10<=$K$5,(1-(($K$5-B10)/$K$5))*$G$2,(1-2*(ABS($K$5-B10))/$K$5)*$G$2) -> #NUM!
A11: Empresa 6 | B11: =+B$4*(1-D11) -> 0 | C11: x | D11: 0.06 | F11: =IF(B11<=$F$5,$G$2*(1-(($F$5-B11)/$F$5)),$G$2*(1-(2*(ABS($F$5-B11)/$F$5)))) -> #DIV/0! | G11: =IF(B11<=$G$5,$G$2*(1-(($G$5-B11)/$G$5)),$G$2*(1-(2*(ABS($G$5-B11)/$G$5)))) -> #NUM! | H11: =IF(B11<=$H$5,$G$2*(1-(($H$5-B11)/$H$5)),$G$2*(1-(2*(ABS($H$5-B11)/$H$5)))) -> #NUM! | I11: =IF(B11<=$I$5,$G$2*(1-(($I$5-B11)/$I$5)),$G$2*(1-(2*(ABS($I$5-B11)/$I$5)))) -> #DIV/0! | J11: =IF(B11<=$J$5,$G$2*(1-(($J$5-B11)/$J$5)),$G$2*(1-2*(ABS($J$5-B11)/$J$5))) -> #DIV/0! | K11: =IF(B11<=$K$5,(1-(($K$5-B11)/$K$5))*$G$2,(1-2*(ABS($K$5-B11))/$K$5)*$G$2) -> #NUM!
A12: Empresa 7 | B12: =+B$4*(1-D12) -> 0 | C12: x | D12: 0.07 | F12: =IF(B12<=$F$5,$G$2*(1-(($F$5-B12)/$F$5)),$G$2*(1-(2*(ABS($F$5-B12)/$F$5)))) -> #DIV/0! | G12: =IF(B12<=$G$5,$G$2*(1-(($G$5-B12)/$G$5)),$G$2*(1-(2*(ABS($G$5-B12)/$G$5)))) -> #NUM! | H12: =IF(B12<=$H$5,$G$2*(1-(($H$5-B12)/$H$5)),$G$2*(1-(2*(ABS($H$5-B12)/$H$5)))) -> #NUM! | I12: =IF(B12<=$I$5,$G$2*(1-(($I$5-B12)/$I$5)),$G$2*(1-(2*(ABS($I$5-B12)/$I$5)))) -> #DIV/0! | J12: =IF(B12<=$J$5,$G$2*(1-(($J$5-B12)/$J$5)),$G$2*(1-2*(ABS($J$5-B12)/$J$5))) -> #DIV/0! | K12: =IF(B12<=$K$5,(1-(($K$5-B12)/$K$5))*$G$2,(1-2*(ABS($K$5-B12))/$K$5)*$G$2) -> #NUM!
A13: Empresa 8 | B13: =+B$4*(1-D13) -> 0 | C13: x | D13: 0.08 | F13: =IF(B13<=$F$5,$G$2*(1-(($F$5-B13)/$F$5)),$G$2*(1-(2*(ABS($F$5-B13)/$F$5)))) -> #DIV/0! | G13: =IF(B13<=$G$5,$G$2*(1-(($G$5-B13)/$G$5)),$G$2*(1-(2*(ABS($G$5-B13)/$G$5)))) -> #NUM! | H13: =IF(B13<=$H$5,$G$2*(1-(($H$5-B13)/$H$5)),$G$2*(1-(2*(ABS($H$5-B13)/$H$5)))) -> #NUM! | I13: =IF(B13<=$I$5,$G$2*(1-(($I$5-B13)/$I$5)),$G$2*(1-(2*(ABS($I$5-B13)/$I$5)))) -> #DIV/0! | J13: =IF(B13<=$J$5,$G$2*(1-(($J$5-B13)/$J$5)),$G$2*((1-2)*(ABS($J$5-B13)/J12))) -> #DIV/0! | K13: =IF(B13<=$K$5,(1-(($K$5-B13)/$K$5))*$G$2,(1-2*(ABS($K$5-B13))/$K$5)*$G$2) -> #NUM!
A14: Empresa 9 | B14: =+B$4*(1-D14) -> 0 | C14: x | D14: 0.09 | F14: =IF(B14<=$F$5,$G$2*(1-(($F$5-B14)/$F$5)),$G$2*(1-(2*(ABS($F$5-B14)/$F$5)))) -> #DIV/0! | G14: =IF(B14<=$G$5,$G$2*(1-(($G$5-B14)/$G$5)),$G$2*(1-(2*(ABS($G$5-B14)/$G$5)))) -> #NUM! | H14: =IF(B14<=$H$5,$G$2*(1-(($H$5-B14)/$H$5)),$G$2*(1-(2*(ABS($H$5-B14)/$H$5)))) -> #NUM! | I14: =IF(B14<=$I$5,$G$2*(1-(($I$5-B14)/$I$5)),$G$2*(1-(2*(ABS($I$5-B14)/$I$5)))) -> #DIV/0! | J14: =IF(B14<=$J$5,$G$2*(1-(($J$5-B14)/$J$5)),$G$2*((1-2)*(ABS($J$5-B14)/J13))) -> #DIV/0! | K14: =IF(B14<=$K$5,(1-(($K$5-B14)/$K$5))*$G$2,(1-2*(ABS($K$5-B14))/$K$5)*$G$2) -> #NUM!
B16: # Pptas Válidas Habilitadas | C16: =COUNTIF(C6:C15,"x") -> 9

Sheet IndicadoresSG
C1: SG
B2: Activo Corriente | C2: 6414628000
B3: Pasivo Corriente | C3: 3136573000
B4: Activo Total | C4: 10274172000
B5: Pasivo total | C5: 3136537000
B6: Utilidad Operacional | C6: 535991000
B7: Gastos de Intereses | C7: 199009000
B8: Índice de Liquidez | C8: =$C$2/$C$3 -> 2.0451072
B9: Capital de Trabajo | C9: =+C2-C3 -> 3278055000
B10: Índice de Endeudamiento | C10: =C5/C4 -> 0.30528368
B11: Razón de Cobertura | C11: =C6/C7 -> 2.6933003
B12: Patrimonio | C12: 7137635000
B13: Rentabilidad del patrimonio | C13: =C6/C12 -> 0.075093641
B14: Rentabilidad del activo | C14: =C6/C4 -> 0.052168778
B17: Indicadores financieros | C17: SOFTGIC | D17: REQUERIDO
B18: Índice de Liquidez | C18: 2.04 | D18: =FichaTecnica!D20 -> 0
B19: Índice de Endeudamiento | C19: 0.3 | D19: =FichaTecnica!D21 -> 0
B20: Razón de Cobertura a intereses | C20: 2037.98 | D20: =FichaTecnica!D22 -> 0
B21: Capital de Trabajo | C21: =C9 -> 3278055000 | D21: =FichaTecnica!D23 -> 0
B22: Indicadores organizacionales | C22: SOFTGIC | D22: REQUERIDO
B23: Rentabilidad del patrimonio | C23: 0.07 | D23: =FichaTecnica!D26 -> 0
B24: Rentabilidad del activo | C24: 0.05 | D24: =FichaTecnica!D27 -> 0

Sheet Indicadores en UT
D1: 1 | E1: 0.5
D2: SG | E2: Empresa 2
B3: Activo Corriente | D3: 6041138000 | E3: 0
B4: Pasivo Corriente | D4: 3620302000 | E4: 0
B5: Activo Total | D5: 9420955000 | E5: 0
B6: Pasivo total | D6: 3620302000 | E6: 0
B7: Utilidad Operacional | D7: 881499000 | E7: 0
B8: Gastos de Intereses | D8: 51182901 | E8: 0
B9: Índice de Liquidez | D9: =D3/D4 -> 1.6686834 | E9: =E3/E4 -> #DIV/0!
B10: Capital de Trabajo | D10: =D3-D4 -> 2420836000 | E10: =E3-E4 -> 0
B11: Índice de Endeudamiento | D11: =D6/D5 -> 0.38428185 | E11: =E6/E5 -> #DIV/0!
B12: Razón de Cobertura | D12: =D7/D8 -> 17.222529 | E12: =E7/E8 -> #DIV/0!
B13: Patrimonio | D13: 4739593339 | E13: 0
B15: Nota: modificar los indicadores según el proceso
D16: Opción 1 - Según % Participación | G16: Opción 2
B17: Indice de Liquidez | C17: =FichaTecnica!D20 -> 0 | D17: =((D3/D4)*$D$1)+((E3/E4)*$E$1) -> #DIV/0! | G17: =((D3)+(E3))/((D4)+(E4)) -> 1.6686834 | H17: >=1.5
B18: Indice de Endeudamiento | C18: =FichaTecnica!D21 -> 0 | D18: =((D6*$D$1)+(E6*$E$1))/((D5*$D$1)+(E5*$E$1)) -> 0.38428185 | G18: =((D6)+(E6))/((D5)+(E5)) -> 0.38428185 | H18: <=75%
B19: Razón de Cobertura de Intereses | C19: =FichaTecnica!D22 -> 0 | D19: =((D7*$D$1)+(E7*$E$1))/((D8*$D$1)+(E8*$E$1)) -> 17.222529 | G19: =((D7)+(E7))/((D8)+(E8)) -> 17.222529 | H19: >=1.3
B20: Capital de Trabajo | C20: =FichaTecnica!D23 -> 0 | D20: =(D10*D1)+(E10*E1) -> 2420836000 | G20: =D10+E10 -> 2420836000 | H20: >=20% Ptto Oficial
B21: Rentabilidad del Patrimonio | C21: =FichaTecnica!D26 -> 0 | D21: =((D7*$D$1)+(E7*E1))/((D13*$D$1)+(E13*$E$1)) -> 0.18598621 | G21: =((D7)+(E7))/((D13)+(E13)) -> 0.18598621 | H21: >=1%
B22: Rentabilidad del Activo | C22: =FichaTecnica!D27 -> 0 | D22: =((D7*$D$1)+(E7*E1))/((D5*$D$1)+(E5*$E$1)) -> 0.093567903 | G22: =((D7)+(E7))/((D5)+(E5)) -> 0.093567903 | H22: >=1%

Sheet CalculoFechas
D1: AÑOS | E1: MESES | F1: DIAS
A2: EXPERIENCIA HABILITANTE | D2: =(DAYS360(B2,C2,FALSE))/360 -> 0 | E2: =(D2)*12 -> 0 | F2: =(E2-2)*30 -> -60
A3: EXPERIENCIA ESPECIFICA | D3: =(DAYS360(B3,C3,FALSE))/360 -> 0 | E3: =(D3)*12 -> 0 | F3: =(E3-2)*30 -> -60
A4: EXPERIENCIA PERFILES | D4: =(DAYS360(B4,C4,FALSE))/360 -> 0 | E4: =(D4)*12 -> 0 | F4: =(E4-2)*30 -> -60
D5: =(DAYS360(B5,C5,FALSE))/360 -> 0 | E5: =(D5)*12 -> 0 | F5: =(E5-2)*30 -> -60
D6: =(DAYS360(B6,C6,FALSE))/360 -> 0 | E6: =(D6)*12 -> 0 | F6: =(E6-2)*30 -> -60
D7: =(DAYS360(B7,C7,FALSE))/360 -> 0 | E7: =(D7)*12 -> 0 | F7: =(E7-2)*30 -> -60
D8: =(DAYS360(B8,C8,FALSE))/360 -> 0 | E8: =(D8)*12 -> 0 | F8: =(E8-2)*30 -> -60
D9: =(DAYS360(B9,C9,FALSE))/360 -> 0 | E9: =(D9)*12 -> 0 | F9: =(E9-2)*30 -> -60
D10: =(DAYS360(B10,C10,FALSE))/360 -> 0 | E10: =(D10)*12 -> 0 | F10: =(E10-2)*30 -> -60
D11: =(DAYS360(B11,C11,FALSE))/360 -> 0 | E11: =(D11)*12 -> 0 | F11: =(E11-2)*30 -> -60
D12: =(DAYS360(B12,C12,FALSE))/360 -> 0 | E12: =(D12)*12 -> 0 | F12: =(E12-2)*30 -> -60
D13: =(DAYS360(B13,C13,FALSE))/360 -> 0 | E13: =(D13)*12 -> 0 | F13: =(E13-2)*30 -> -60
D14: =(DAYS360(B14,C14,FALSE))/360 -> 0 | E14: =(D14)*12 -> 0 | F14: =(E14-2)*30 -> -60
D15: =(DAYS360(B15,C15,FALSE))/360 -> 0 | E15: =(D15)*12 -> 0 | F15: =(E15-2)*30 -> -60
D16: =(DAYS360(B16,C16,FALSE))/360 -> 0 | E16: =(D16)*12 -> 0 | F16: =(E16-2)*30 -> -60
... D43: =(DAYS360(B43,C43,FALSE))/360 -> 0 | E43: =(D43)*12 -> 0 | F43: =(E43-2)*30 -> -60
